[
    {
        "name": "niko",
        "linksUrl": "https://nikoslinks.netlify.app/"
    },
    {
        "name": "Renat",
        "linksUrl": "https://renat-khambazarov-netlify-linkssharing.netlify.app/"
    },
    {
        "name": "Pierluigi",
        "linksUrl": "https://fbwd01linkspier.netlify.app/"
    },
    {
        "name": "Giacomo",
        "linksUrl": "https://fbwd01linksgiacomo.netlify.app/"
    },
    {
        "name": "Rene",
        "linksUrl": "https://linkcollection.netlify.app/"
    },
    {
        "name": "Edward",
        "linksUrl": "https://fbwd01linksedward.netlify.app/"
    }
]